{"button_size":20,"tree":"skilltree:tree","background_texture":"skilltree:textures/icons/background/notable.png","icon_texture":"skilltree:textures/icons/miner_subclass_1_offensive_notable_1.png","tooltip_texture":"skilltree:textures/tooltip/notable.png","attribute_modifiers":[{"attribute":"minecraft:generic.attack_speed","amount":0.05,"operation":"multiply_base"},{"attribute":"minecraft:generic.movement_speed","amount":0.05,"operation":"multiply_base"}],"position":{"x":-438.90466,"y":118.704544},"connections":[]}