{"button_size":24,"tree":"skilltree:tree","background_texture":"skilltree:textures/icons/background/keystone.png","icon_texture":"skilltree:textures/icons/miner_offensive_crafting_keystone_1.png","tooltip_texture":"skilltree:textures/tooltip/keystone.png","attribute_modifiers":[{"attribute":"skilltree:gem_power_in_weapon","amount":0.3,"operation":"multiply_base"},{"attribute":"skilltree:maximum_weapon_sockets","amount":1.0,"operation":"addition"}],"position":{"x":-348.65372,"y":74.993515},"connections":[]}